[{"name":"com.brewedink.postuss","repoUrl":"https://github.com/cdhanna/postUSS","displayName":"BrewedInk PostUSS","description":"transpile modern CSS to USS","licenseSpdxId":"MIT","licenseName":"MIT License","topics":["code-generation","editor-enhancement","gui","utilities"],"hunter":"cdhanna","createdAt":1637606208268,"image":null,"parentRepoUrl":null,"readme":"master:UnityGame/Packages/com.brewedink.postuss/readme.md","gitTagPrefix":"","gitTagIgnore":"","minVersion":"","displayName_zhCN":"","description_zhCN":"","readme_zhCN":"","imageFit":"cover","repo":"postUSS","owner":"cdhanna","ownerUrl":"https://github.com/cdhanna","parentRepo":null,"parentOwner":null,"parentOwnerUrl":null,"readmeBranch":"master","hunterUrl":"https://github.com/cdhanna"}]