[{"name":"com.ms-lima.photonserializer","repoUrl":"https://github.com/MS-LIMA/PhotonSerializer","displayName":"Photon Serializer","description":"This plugin provides custom type registering method with script and compares the difference with other serialization methods.","licenseSpdxId":"MIT","licenseName":"MIT License","topics":["network","utilities"],"hunter":"uurha","createdAt":1671916680518,"image":"","parentRepoUrl":null,"readme":"upm:README.md","gitTagPrefix":"","gitTagIgnore":"","minVersion":"","displayName_zhCN":"","description_zhCN":"","readme_zhCN":"","imageFit":"cover","repo":"PhotonSerializer","owner":"MS-LIMA","ownerUrl":"https://github.com/MS-LIMA","parentRepo":null,"parentOwner":null,"parentOwnerUrl":null,"readmeBranch":"upm","hunterUrl":"https://github.com/uurha"}]