[{"name":"com.matthewminer.bigimagerecorder","displayName":"Big Image Recorder","description":"Recorder to capture image sequences that exceed Unity's maximum texture size.","repoUrl":"https://github.com/mminer/big-image-recorder","parentRepoUrl":null,"licenseSpdxId":"MIT","licenseName":"MIT License","topics":["camera","editor-enhancement"],"hunter":"JesseTG","gitTagPrefix":"","gitTagIgnore":"","minVersion":"","image":"https://github.com/mminer/big-image-recorder/raw/80befb9b71d460237dc656280774724254321f6b/Documentation~/tiles-stitched.jpg","readme":"master:README.md","readme_zhCN":"","displayName_zhCN":"","description_zhCN":"","createdAt":1627223114601,"imageFit":"cover","repo":"big-image-recorder","owner":"mminer","ownerUrl":"https://github.com/mminer","parentRepo":null,"parentOwner":null,"parentOwnerUrl":null,"readmeBranch":"master","hunterUrl":"https://github.com/JesseTG"},{"name":"com.matthewminer.consolation","displayName":"Consolation","description":"In-game debug console for Unity.","repoUrl":"https://github.com/mminer/consolation","parentRepoUrl":null,"licenseSpdxId":"MIT","licenseName":"MIT License","topics":["debugging-and-logging","gui"],"hunter":"JesseTG","gitTagPrefix":"","gitTagIgnore":"","minVersion":"","image":null,"readme":"master:README.md","readme_zhCN":"","displayName_zhCN":"","description_zhCN":"","createdAt":1627222945549,"imageFit":"cover","repo":"consolation","owner":"mminer","ownerUrl":"https://github.com/mminer","parentRepo":null,"parentOwner":null,"parentOwnerUrl":null,"readmeBranch":"master","hunterUrl":"https://github.com/JesseTG"},{"name":"com.matthewminer.hierarchy-icons","displayName":"Hierarchy Icons","description":"Show component icons in the Hierarchy.","repoUrl":"https://github.com/mminer/hierarchy-icons","parentRepoUrl":null,"licenseSpdxId":"MIT","licenseName":"MIT License","topics":["editor-enhancement"],"hunter":"JesseTG","gitTagPrefix":"","gitTagIgnore":"","minVersion":"","image":"https://camo.githubusercontent.com/571cfb391ec15748e7f48fb049ef36519800d4bf8c42fce61e1b9027d10b86e0/687474703a2f2f6d6174746865776d696e65722e636f6d2f696d616765732f6869657261726368792d69636f6e732e706e67","readme":"upm-package:README.md","readme_zhCN":"","displayName_zhCN":"","description_zhCN":"","createdAt":1627223229541,"imageFit":"cover","repo":"hierarchy-icons","owner":"mminer","ownerUrl":"https://github.com/mminer","parentRepo":null,"parentOwner":null,"parentOwnerUrl":null,"readmeBranch":"upm-package","hunterUrl":"https://github.com/JesseTG"},{"name":"com.matthewminer.recorderpluginstarter","displayName":"Recorder Plugin Starter","description":"Bare-bones Recorder plugin to use as starting point.","repoUrl":"https://github.com/mminer/recorder-plugin-starter","parentRepoUrl":null,"licenseSpdxId":null,"licenseName":"","topics":["camera","editor-enhancement"],"hunter":"JesseTG","gitTagPrefix":"","gitTagIgnore":"","minVersion":"","image":null,"readme":"master:README.md","readme_zhCN":"","displayName_zhCN":"","description_zhCN":"","createdAt":1627223158981,"imageFit":"cover","repo":"recorder-plugin-starter","owner":"mminer","ownerUrl":"https://github.com/mminer","parentRepo":null,"parentOwner":null,"parentOwnerUrl":null,"readmeBranch":"master","hunterUrl":"https://github.com/JesseTG"}]