[{"name":"com.sleepyape.framework","repoUrl":"https://github.com/sickape/sleepyape-framework","displayName":"SleepyApe Framework","description":"ScriptableObject based framework.","licenseSpdxId":"MIT","licenseName":"MIT License","topics":["frameworks"],"hunter":"","createdAt":1619733930159,"image":null,"parentRepoUrl":null,"readme":"main:README.md","gitTagPrefix":"","gitTagIgnore":"","minVersion":"","displayName_zhCN":"","description_zhCN":"","readme_zhCN":"","imageFit":"cover","repo":"sleepyape-framework","owner":"sickape","ownerUrl":"https://github.com/sickape","parentRepo":null,"parentOwner":null,"parentOwnerUrl":null,"readmeBranch":"main","hunterUrl":null}]