[{"name":"com.mxr.unity.sdk","repoUrl":"https://github.com/ManageXR/mxr-unity-sdk","displayName":"ManageXR Unity SDK","description":"ManageXR Android and Editor System and Utilities for integrating with the ManageXR MDM platform.","licenseSpdxId":"","licenseName":"ManageXR SDK License","topics":["ar-and-vr","integration"],"hunter":"adrenak","createdAt":1674042201619,"image":"","parentRepoUrl":null,"readme":"upm@latest:README.md","gitTagPrefix":"","gitTagIgnore":"","minVersion":"","displayName_zhCN":"","description_zhCN":"","readme_zhCN":"","imageFit":"cover","repo":"mxr-unity-sdk","owner":"ManageXR","ownerUrl":"https://github.com/ManageXR","parentRepo":null,"parentOwner":null,"parentOwnerUrl":null,"readmeBranch":"upm@latest","hunterUrl":"https://github.com/adrenak"}]