[{"name":"com.ronpad.entities","displayName":"Com.RonPad.Entities","description":"An entity framework","repoUrl":"https://github.com/rontian/Com.RonPad.Entities","parentRepoUrl":null,"licenseSpdxId":"MIT","licenseName":"MIT License","topics":["dots-and-ecs","frameworks"],"hunter":"rontian","gitTagPrefix":"","gitTagIgnore":"","minVersion":"","image":null,"readme":"master:README.md","readme_zhCN":"","displayName_zhCN":"","description_zhCN":"","createdAt":1627379240666,"imageFit":"cover","repo":"Com.RonPad.Entities","owner":"rontian","ownerUrl":"https://github.com/rontian","parentRepo":null,"parentOwner":null,"parentOwnerUrl":null,"readmeBranch":"master","hunterUrl":"https://github.com/rontian"},{"name":"com.ronpad.signals","displayName":"Com.RonPad.Signals","description":"Think Outside the Event","repoUrl":"https://github.com/rontian/Com.RonPad.Signals","parentRepoUrl":null,"licenseSpdxId":"MIT","licenseName":"MIT License","topics":["utilities"],"hunter":"rontian","gitTagPrefix":"","gitTagIgnore":"","minVersion":"","image":null,"readme":"master:README.md","readme_zhCN":"","displayName_zhCN":"","description_zhCN":"","createdAt":1626835782682,"imageFit":"cover","repo":"Com.RonPad.Signals","owner":"rontian","ownerUrl":"https://github.com/rontian","parentRepo":null,"parentOwner":null,"parentOwnerUrl":null,"readmeBranch":"master","hunterUrl":"https://github.com/rontian"}]