[{"name":"com.richtools.filebasedplayerprefs","displayName":"File Based Player Prefs","description":"PlayerPrefs substitute that saves player prefs data in a json file.","repoUrl":"https://github.com/richardelms/FileBasedPlayerPrefs","parentRepoUrl":null,"licenseSpdxId":"MIT","licenseName":"MIT License","topics":["data-management"],"hunter":"JesseTG","gitTagPrefix":"","gitTagIgnore":"","minVersion":"","image":null,"readme":"master:README.md","readme_zhCN":"","displayName_zhCN":"","description_zhCN":"","createdAt":1637437582734,"imageFit":"cover","repo":"FileBasedPlayerPrefs","owner":"richardelms","ownerUrl":"https://github.com/richardelms","parentRepo":null,"parentOwner":null,"parentOwnerUrl":null,"readmeBranch":"master","hunterUrl":"https://github.com/JesseTG"}]