[{"name":"com.glib.arunityx","repoUrl":"https://github.com/VGA-GLAB/G-Lab-Library","displayName":"Glib","description":"UPM fork of arunityx","licenseSpdxId":"MIT","licenseName":"MIT License","topics":["frameworks"],"hunter":"VGA-GLAB","createdAt":1687647666527,"image":"","parentRepoUrl":null,"readme":"main:README.md","gitTagPrefix":"","gitTagIgnore":"","minVersion":"","displayName_zhCN":"","description_zhCN":"","readme_zhCN":"","imageFit":"cover","repo":"G-Lab-Library","owner":"VGA-GLAB","ownerUrl":"https://github.com/VGA-GLAB","parentRepo":null,"parentOwner":null,"parentOwnerUrl":null,"readmeBranch":"main","hunterUrl":"https://github.com/VGA-GLAB"}]