[{"name":"com.kingdox.uniflux","repoUrl":"https://github.com/kingdox/UniFlux","displayName":"UniFlux","description":"Provides an method pub/sub flow integration to Unity.","licenseSpdxId":"MIT","licenseName":"MIT License","topics":["frameworks","integration"],"hunter":"kingdox","createdAt":1679702148573,"image":"","parentRepoUrl":null,"readme":"main:README.md","gitTagPrefix":"","gitTagIgnore":"","minVersion":"","displayName_zhCN":"","description_zhCN":"","readme_zhCN":"","imageFit":"cover","repo":"UniFlux","owner":"kingdox","ownerUrl":"https://github.com/kingdox","parentRepo":null,"parentOwner":null,"parentOwnerUrl":null,"readmeBranch":"main","hunterUrl":"https://github.com/kingdox"}]