[{"name":"com.medallyon.savemanager","repoUrl":"https://github.com/medallyon/unity-savemanager","displayName":"SaveManager","description":"A custom Unity SaveManager that allows easy saving & loading of Variables in any of your Scripts.","licenseSpdxId":"","licenseName":"ISC","topics":["data-management"],"hunter":"medallyon","createdAt":1655219316353,"image":"","parentRepoUrl":null,"readme":"master:README.md","gitTagPrefix":"","gitTagIgnore":"","minVersion":"","displayName_zhCN":"","description_zhCN":"","readme_zhCN":"","imageFit":"cover","repo":"unity-savemanager","owner":"medallyon","ownerUrl":"https://github.com/medallyon","parentRepo":null,"parentOwner":null,"parentOwnerUrl":null,"readmeBranch":"master","hunterUrl":"https://github.com/medallyon"}]