[{"name":"com.volorf.figma-ui-image","repoUrl":"https://github.com/Volorf/figma-ui-image","displayName":"Figma UI Image","description":"Bring your design from Figma to Unity as a UI Image with a few clicks.","licenseSpdxId":"MIT","licenseName":"MIT License","topics":["2d","asset-management","data-management","editor-enhancement","frameworks","gui","integration","procedural-generation","sprite-management","utilities"],"hunter":"StephenHodgson","createdAt":1707582412935,"image":"","parentRepoUrl":null,"readme":"main:README.md","gitTagPrefix":"","gitTagIgnore":"","minVersion":"","imageFit":"cover","repo":"figma-ui-image","owner":"Volorf","ownerUrl":"https://github.com/Volorf","parentRepo":null,"parentOwner":null,"parentOwnerUrl":null,"readmeBranch":"main","hunterUrl":"https://github.com/StephenHodgson"}]