[{"name":"io.chainsafe.web3-unity.lootboxes","repoUrl":"https://github.com/ChainSafe/web3.unity","displayName":"web3.unity SDK Lootboxes","description":"This additional package provides you with sample scene and sample scripts for opening lootboxes of various types","licenseSpdxId":"LGPL-3.0","licenseName":"GNU Lesser General Public License v3.0 only","topics":["data-management","network"],"hunter":"kantagara","createdAt":1706533237231,"image":"","parentRepoUrl":null,"readme":"main:Packages/io.chainsafe.web3-unity.lootboxes/README.md","gitTagPrefix":"io.chainsafe.web3-unity.lootboxes/","gitTagIgnore":"","minVersion":"","imageFit":"cover","repo":"web3.unity","owner":"ChainSafe","ownerUrl":"https://github.com/ChainSafe","parentRepo":null,"parentOwner":null,"parentOwnerUrl":null,"readmeBranch":"main","hunterUrl":"https://github.com/kantagara"},{"name":"io.chainsafe.web3-unity.web3auth","repoUrl":"https://github.com/ChainSafe/web3.unity","displayName":"web3.unity SDK Web3Auth Plugin","description":"Web3Atuh service support for web3.untiy SDK. Easy users onboarding, one of the ways to handle private keys.","licenseSpdxId":"LGPL-3.0","licenseName":"GNU Lesser General Public License v3.0 only","topics":["frameworks","integration","utilities","network","services"],"hunter":"kalambet","createdAt":1695632274872,"image":"","parentRepoUrl":null,"readme":"main:README.md","gitTagPrefix":"io.chainsafe.web3-unity.web3auth/","gitTagIgnore":"","minVersion":"2.5.0","displayName_zhCN":"","description_zhCN":"","readme_zhCN":"","imageFit":"cover","repo":"web3.unity","owner":"ChainSafe","ownerUrl":"https://github.com/ChainSafe","parentRepo":null,"parentOwner":null,"parentOwnerUrl":null,"readmeBranch":"main","hunterUrl":"https://github.com/kalambet"},{"name":"io.chainsafe.web3-unity","repoUrl":"https://github.com/ChainSafe/web3.unity","displayName":"web3.unity SDK","description":"web3.unity is an open-source gaming SDK written in C# and developed by ChainSafe Gaming. It connects games built in the Unity game engine to the blockchain. The library currently supports games built for web browsers (WebGL), iOS/Android mobile, and desktop. web3.unity is compatible with most EVM-based chains such as Ethereum, Polygon, Moonbeam, Cronos, Nervos, and Binance Smart Chain, letting developers easily choose and switch between them to create the best in-game experience.","licenseSpdxId":"LGPL-3.0","licenseName":"GNU Lesser General Public License v3.0 only","topics":["frameworks","integration","utilities","network","services"],"hunter":"kalambet","createdAt":1695632274872,"image":"","parentRepoUrl":null,"readme":"main:README.md","gitTagPrefix":"io.chainsafe.web3-unity/","gitTagIgnore":"","minVersion":"2.5.0","displayName_zhCN":"","description_zhCN":"","readme_zhCN":"","imageFit":"cover","repo":"web3.unity","owner":"ChainSafe","ownerUrl":"https://github.com/ChainSafe","parentRepo":null,"parentOwner":null,"parentOwnerUrl":null,"readmeBranch":"main","hunterUrl":"https://github.com/kalambet"}]