[{"name":"io.livekit.unity","repoUrl":"https://github.com/livekit/client-sdk-unity-web","displayName":"LiveKit WebGL SDK","description":"LiveKit Unity Bridge for WebGL","licenseSpdxId":"Apache-2.0","licenseName":"Apache License 2.0","topics":["frameworks","integration","network","services","utilities","video"],"hunter":"julienkay","createdAt":1682109275902,"image":"","parentRepoUrl":null,"readme":"main:README.md","gitTagPrefix":"","gitTagIgnore":"","minVersion":"","displayName_zhCN":"","description_zhCN":"","readme_zhCN":"","imageFit":"cover","repo":"client-sdk-unity-web","owner":"livekit","ownerUrl":"https://github.com/livekit","parentRepo":null,"parentOwner":null,"parentOwnerUrl":null,"readmeBranch":"main","hunterUrl":"https://github.com/julienkay"}]