[{"name":"io.megamiley.change-camera-aim-on-start","repoUrl":"https://github.com/MileyHollenberg/ChangeCameraAimOnStart","displayName":"Change Camera Aim On Start","description":"Ever wanted to start your game from the scene views position instead of the camera position? Look no further!","licenseSpdxId":"MIT","licenseName":"MIT License","topics":["camera","editor-enhancement","utilities"],"hunter":"MileyHollenberg","createdAt":1591371997191,"image":null,"parentRepoUrl":null,"readme":"master:README.md","gitTagPrefix":"","gitTagIgnore":"","minVersion":"","displayName_zhCN":"Change Camera Aim On Start","description_zhCN":"是否曾经想从场景视图位置而不是摄影机位置开始游戏？这正是你需要的。","imageFit":"cover","repo":"ChangeCameraAimOnStart","owner":"MileyHollenberg","ownerUrl":"https://github.com/MileyHollenberg","parentRepo":null,"parentOwner":null,"parentOwnerUrl":null,"readmeBranch":"master","hunterUrl":"https://github.com/MileyHollenberg"},{"name":"io.megamiley.event-visualizer","repoUrl":"https://github.com/MileyHollenberg/EventVisualizer","displayName":"Event Visualizer","description":"Visualize UnityEvent calls within the editor, both incoming and outgoing.","licenseSpdxId":"MIT","licenseName":"MIT License","topics":["editor-enhancement","level-design","utilities"],"hunter":"MileyHollenberg","createdAt":1593328132173,"image":null,"parentRepoUrl":null,"readme":"master:README.md","gitTagPrefix":"","gitTagIgnore":"","minVersion":"","displayName_zhCN":"事件可视化","description_zhCN":"在编辑器中可视化UnityEvent调用（传入和传出）。","imageFit":"cover","repo":"EventVisualizer","owner":"MileyHollenberg","ownerUrl":"https://github.com/MileyHollenberg","parentRepo":null,"parentOwner":null,"parentOwnerUrl":null,"readmeBranch":"master","hunterUrl":"https://github.com/MileyHollenberg"},{"name":"io.megamiley.prefab-asset-utility","repoUrl":"https://github.com/MileyHollenberg/PrefabAssetUtility","displayName":"PrefabAssetUtility","description":"Utility package that allows you to get all prefabs using a certain asset and visa versa.","licenseSpdxId":"MIT","licenseName":"MIT License","topics":["asset-management","data-management","debugging-and-logging","frameworks","utilities"],"hunter":"MileyHollenberg","createdAt":1592605361723,"image":null,"parentRepoUrl":null,"readme":"master:README.md","gitTagPrefix":"","gitTagIgnore":"","minVersion":"","displayName_zhCN":"PrefabAssetUtility","description_zhCN":"该实用程序包可让您使用某种资源来获得所有Prefab，反之亦然。","imageFit":"cover","repo":"PrefabAssetUtility","owner":"MileyHollenberg","ownerUrl":"https://github.com/MileyHollenberg","parentRepo":null,"parentOwner":null,"parentOwnerUrl":null,"readmeBranch":"master","hunterUrl":"https://github.com/MileyHollenberg"},{"name":"io.megamiley.rigidbody-center-of-mass-editor","repoUrl":"https://github.com/MileyHollenberg/RigidbodyCenterOfMassEditor","displayName":"Rigidbody Center Of Mass Editor","description":"Allows you to change the center of mass of Rigidbodies within the Unity editor","licenseSpdxId":"MIT","licenseName":"MIT License","topics":["editor-enhancement","level-design","utilities"],"hunter":"MileyHollenberg","createdAt":1591450265147,"image":null,"parentRepoUrl":null,"readme":"master:README.md","gitTagPrefix":"","gitTagIgnore":"","minVersion":"","displayName_zhCN":"Rigidbody质量中心编辑器","description_zhCN":"允许您在Unity编辑器中更改Rigidbody的重心","imageFit":"cover","repo":"RigidbodyCenterOfMassEditor","owner":"MileyHollenberg","ownerUrl":"https://github.com/MileyHollenberg","parentRepo":null,"parentOwner":null,"parentOwnerUrl":null,"readmeBranch":"master","hunterUrl":"https://github.com/MileyHollenberg"}]