[{"name":"net.wraithavengames.firstsight","repoUrl":"https://github.com/TheDudeFromCI/FirstSight","displayName":"FirstSight","description":"A first person controller plugin written for Unity.","licenseSpdxId":"MIT","licenseName":"MIT License","topics":["camera","physics","utilities"],"hunter":"TheDudeFromCI","createdAt":1590714703814,"image":null,"parentRepoUrl":null,"readme":"master:README.md","gitTagPrefix":"","gitTagIgnore":"","minVersion":"","displayName_zhCN":"FirstSight","description_zhCN":"为Unity编写的第一人称控制器插件。","imageFit":"cover","repo":"FirstSight","owner":"TheDudeFromCI","ownerUrl":"https://github.com/TheDudeFromCI","parentRepo":null,"parentOwner":null,"parentOwnerUrl":null,"readmeBranch":"master","hunterUrl":"https://github.com/TheDudeFromCI"},{"name":"net.wraithavengames.unityinterfacesupport","repoUrl":"https://github.com/TheDudeFromCI/Unity-Interface-Support","displayName":"Unity Interface Support","description":"A simply implementation which allows for interface-type fields to be accepted in the Unity inspector.","licenseSpdxId":"MIT","licenseName":"MIT License","topics":["editor-enhancement","utilities"],"hunter":"TheDudeFromCI","createdAt":1591602164696,"image":null,"parentRepoUrl":null,"readme":"master:README.md","gitTagPrefix":"","gitTagIgnore":"","minVersion":"","displayName_zhCN":"Unity接口支持","description_zhCN":"一个简单的实现，它允许接口类型字段在Unity inspector中被接受。","imageFit":"cover","repo":"Unity-Interface-Support","owner":"TheDudeFromCI","ownerUrl":"https://github.com/TheDudeFromCI","parentRepo":null,"parentOwner":null,"parentOwnerUrl":null,"readmeBranch":"master","hunterUrl":"https://github.com/TheDudeFromCI"}]