[{"name":"net.slothsoft.unity-extensions","repoUrl":"https://github.com/Faulo/UnityExtensions","displayName":"Slothsoft's Unity Extensions","description":"C# extension functions, attributes and editor tools for common Unity problems.","licenseSpdxId":"MIT","licenseName":"MIT License","topics":["editor-enhancement","utilities"],"hunter":"Faulo","createdAt":1610470403918,"image":"","parentRepoUrl":null,"readme":"main:README.md","gitTagPrefix":"","gitTagIgnore":"","minVersion":"","displayName_zhCN":"","description_zhCN":"","readme_zhCN":"","imageFit":"cover","repo":"UnityExtensions","owner":"Faulo","ownerUrl":"https://github.com/Faulo","parentRepo":null,"parentOwner":null,"parentOwnerUrl":null,"readmeBranch":"main","hunterUrl":"https://github.com/Faulo"}]