[{"name":"sh.orels.udontoolkit","repoUrl":"https://github.com/orels1/UdonToolkit","displayName":"Udon Toolkit","description":"A set of purpose-built Udon Behaviours and tools to make your own","licenseSpdxId":"MIT","licenseName":"MIT License","topics":["ar-and-vr","editor-enhancement","gui","utilities"],"hunter":"","createdAt":1629342213841,"image":null,"parentRepoUrl":null,"readme":"master:README.md","gitTagPrefix":"","gitTagIgnore":"","minVersion":"","displayName_zhCN":"","description_zhCN":"","readme_zhCN":"","imageFit":"cover","repo":"UdonToolkit","owner":"orels1","ownerUrl":"https://github.com/orels1","parentRepo":null,"parentOwner":null,"parentOwnerUrl":null,"readmeBranch":"master","hunterUrl":null}]